mcp_server/__init__.py
mcp_server/server.py
calculate_power_mcp_76980-1.0.0.dist-info/LICENSE
calculate_power_mcp_76980-1.0.0.dist-info/METADATA
calculate_power_mcp_76980-1.0.0.dist-info/WHEEL
calculate_power_mcp_76980-1.0.0.dist-info/top_level.txt
calculate_power_mcp_76980-1.0.0.dist-info/RECORD
