Metadata-Version: 2.1
Name: calculate-power-mcp-76980
Version: 1.0.0
Summary: A Model Context Protocol Server implementation
Home-page: https://github.com/mcp-developer/mcp-server
Author: MCP Developer
Author-email: mcp@example.com
License: MIT License
Classifier: Programming Language :: Python :: 3
Classifier: License :: OSI Approved :: MIT License
Classifier: Operating System :: OS Independent
Requires-Python: >=3.7
License-File: LICENSE
Requires-Dist: fastmcp
